[{
  "_id": {
    "$oid": "655a0db33961f9437c3aa268"
  },
  "AuthorEmail": "kingtut10101@gmail.com",
  "ContentType": "map",
  "ContentFilepath": "./media/mapData/Classic_Map.slf",
  "ContentFileSize": 7000,
  "ThumbnailFilepath": "./media/mapData/thumbnails/Classic_Map.png",
  "Title": "Classic Map",
  "Description": "This Map is a certified classic",
  "CreationDate": "2020-03-27T12:12:12.948Z",
  "Downloads": 461,
  "Tags": [
    "Classic",
    "Sand",
    "Game"
  ],
  "UpdatedDate": {
    "$date": "2021-01-17T09:30:13.948Z"
  }
},
{
  "_id": {
    "$oid": "655a0db33961f9437c3aa269"
  },
  "AuthorEmail": "8pp8413@gmail.com",
  "ContentType": "map",
  "ContentFilepath": "./media/mapData/Magma.slf",
  "ContentFileSize": 37000,
  "ThumbnailFilepath": "./media/mapData/thumbnails/Classic_Map.png",
  "Title": "Magma",
  "Description": "Magma",
  "CreationDate": {
    "$date": "2021-12-14T15:41:56.948Z"
  },
  "Downloads": 99999,
  "Tags": [
    "Magma"
  ],
  "UpdatedDate": {
    "$date": "2021-12-14T15:41:56.948Z"
  }
},
{
  "_id": {
    "$oid": "655a0db33961f9437c3aa26a"
  },
  "AuthorEmail": "chrismas@aol.com",
  "ContentType": "map",
  "ContentFilepath": "./media/mapData/File_test.slf",
  "ContentFileSize": 3000,
  "ThumbnailFilepath": "./media/mapData/thumbnails/Classic_Map.png",
  "Title": "File test",
  "Description": "don't mind this",
  "CreationDate": {
    "$date": "2023-11-19T06:03:21.948Z"
  },
  "Downloads": 3,
  "Tags": [
    "Test",
    "Relaxing"
  ],
  "UpdatedDate": {
    "$date": "2023-11-19T06:03:21.948Z"
  }
}]
